verysimplemodule_alison/__init__.py
verysimplemodule_alison/add.py
verysimplemodule_alison/subtract.py
verysimplemodule_alison/extra/__init__.py
verysimplemodule_alison/extra/divide.py
verysimplemodule_alison/extra/multiple.py
verysimplemodule_alison-0.0.5.dist-info/METADATA
verysimplemodule_alison-0.0.5.dist-info/WHEEL
verysimplemodule_alison-0.0.5.dist-info/top_level.txt
verysimplemodule_alison-0.0.5.dist-info/RECORD
