Metadata-Version: 2.1
Name: verysimplemodule-alison
Version: 0.0.5
Summary: My first Python package
Author: Alison
Author-email: alissonmarqueshm30@gmail.com
